{"name": "A. Oriani", "city": "Ravenna", "region": "emi", "fullregion": "Emilia-Romagna", "medals": [0, 3, 5, 4], "editions": [{"num": 17, "title": "17th Edition", "year": "2025/26", "teams": [{"id": "t-emi-049", "name": "gates", "institute": "A. Oriani, Ravenna", "inst_id": "raps01000q", "region": "emi", "fullregion": "Emilia-Romagna", "coach": "Matteo Vitali", "members": "", "finalist": null, "medals": [0, 0, 0, 0], "rank_reg": 31, "rank_tot": 339, "rank_excl": 316, "bestrank": 339, "avgrank": 59.88165680473373, "points": 127, "edition": 17}, {"id": "b-emi-048", "name": "\\Error 404", "institute": "A. Oriani, Ravenna", "inst_id": "raps01000q", "region": "emi", "fullregion": "Emilia-Romagna", "coach": "Matteo Vitali", "members": "", "finalist": null, "medals": [0, 0, 0, 0], "rank_reg": 43, "rank_tot": 538, "rank_excl": 515, "bestrank": 535, "avgrank": 36.68639053254438, "points": 0, "edition": 17}], "medals": [0, 0, 0, 0], "points": 127, "avgrank": 48.28402366863905}, {"num": 16, "title": "16th Edition", "year": "2024/25", "teams": [{"id": "t-emi-059", "name": "oriani_squadra_2", "institute": "A. Oriani, Ravenna", "inst_id": "raps01000q", "region": "emi", "fullregion": "Emilia-Romagna", "coach": "Mario Alsini", "members": "", "finalist": false, "medals": [0, 0, 1, 2], "rank_reg": 21, "rank_tot": 155, "rank_excl": 135, "bestrank": 43, "avgrank": 65.52886641382216, "points": 645, "edition": 16}, {"id": "t-emi-058", "name": "oriani_squadra_1", "institute": "A. Oriani, Ravenna", "inst_id": "raps01000q", "region": "emi", "fullregion": "Emilia-Romagna", "coach": "Mario Alsini", "members": "", "finalist": false, "medals": [0, 0, 1, 0], "rank_reg": 41, "rank_tot": 401, "rank_excl": 380, "bestrank": 65, "avgrank": 45.891276864728184, "points": 200, "edition": 16}, {"id": "t-emi-057", "name": "MarioBros", "institute": "A. Oriani, Ravenna", "inst_id": "raps01000q", "region": "emi", "fullregion": "Emilia-Romagna", "coach": "Mario Alsini", "members": "", "finalist": false, "medals": [0, 0, 0, 0], "rank_reg": 53, "rank_tot": 528, "rank_excl": 507, "bestrank": 332, "avgrank": 34.63969658659924, "points": 0, "edition": 16}], "medals": [0, 0, 2, 2], "points": 845, "avgrank": 48.68661328838319}, {"num": 15, "title": "15th Edition", "year": "2023/24", "teams": [{"id": "t-emi-076", "name": "alfredooo", "institute": "A. Oriani, Ravenna", "inst_id": "raps01000q", "region": "emi", "fullregion": "Emilia-Romagna", "coach": "Monica Signorini", "members": "", "finalist": false, "medals": [0, 1, 2, 1], "rank_reg": 15, "rank_tot": 90, "rank_excl": 73, "bestrank": 30, "avgrank": 84.04175988068606, "points": 867, "edition": 15}], "medals": [0, 1, 2, 1], "points": 867, "avgrank": 84.04175988068606}, {"num": 14, "title": "14th Edition", "year": "2022/23", "teams": [{"id": "t-emi-065", "name": "I_magnifici_4+2", "institute": "A. Oriani, Ravenna", "inst_id": "raps01000q", "region": "emi", "fullregion": "Emilia-Romagna", "coach": "Monica Signorini", "members": "", "finalist": false, "medals": [0, 2, 1, 1], "rank_reg": 7, "rank_tot": 42, "rank_excl": 26, "bestrank": 22, "avgrank": 90.4181892001624, "points": 1501, "edition": 14}], "medals": [0, 2, 1, 1], "points": 1501, "avgrank": 90.4181892001624}], "bestedrank": 42, "bestrank": 22, "bestavgrank": 90.4181892001624, "avgrank": 59.58397661189658, "points": 3340, "participations": [14, 15, 16, 17], "teams": 7, "highlights": [{"id": "/edition/14/team/t-emi-065", "name": "I_magnifici_4+2", "description": "is the team with the best awards (4), rank (42), regional rank (7), average rank (90%) and total points (1501)"}, {"id": "/edition/14", "name": "OIS 2022/23", "description": "is the edition with the most points per team (1501), average rank (90%), total points (1501) and awards (4)"}, {"id": "/edition/16", "name": "OIS 2024/25", "description": "is the edition with the most teams (3)"}]}