{"ed_id": 14, "edition": "14th Edition", "year": "2022/23", "round": "Round 3", "r_id": "3", "ranking": [{"rank": 1, "score": 15, "team": {"id": "t-ven-011", "name": "Gi\u00e0 Lo Giaalo", "institute": "Liceo Scientifico Vittorino da Feltre, Feltre", "inst_id": "blpsd7500d", "region": "ven", "fullregion": "Veneto", "coach": "Nicola Bisetto", "members": "", "finalist": null, "medals": [0, 2, 0, 0], "rank_reg": 6, "rank_tot": 47, "rank_excl": 33, "bestrank": 25, "avgrank": 80.71457572066586, "points": 1040}}], "name": "notdivisible", "title": "Minimum Not Divisible", "statement": "You have a tree (a connected acyclic graph) of N nodes indexed from 1 to N. Each node i has an integer value V_i > 1 assigned to it. You are given Q queries, where each query i consists of two integers A_i and B_i. Your task is to find the minimum value (greater than 1) that is not divisible by any of the assigned values on the path between A_i and B_i, including the values assigned to A_i and B_i.", "points": 15, "medpos": 15, "avgpos": 15.0, "average": 0.018270401948842874, "highest": 15, "positive": 1, "fullscore": 100, "fullscores": 0, "highlights": [{"id": "/region/ven/blpsd7500d", "name": "Liceo Scientifico Vittorino da Feltre, Feltre", "description": "is the institute with the most points (15)"}, {"id": "/region/ven", "name": "Veneto", "description": "is the region with the most points (15)"}]}