{"name": "Bodoni", "city": "Parma", "region": "emi", "fullregion": "Emilia Romagna", "medals": [0, 0, 0, 3], "editions": {"6": [{"id": "umaireiv", "name": "Bodoni", "institute": "Bodoni, Parma", "inst_id": "prtd04000q", "region": "emi", "fullregion": "Emilia Romagna", "coach": "", "members": "", "finalist": true, "medals": [0, 0, 0, 0], "rank_reg": 16, "rank_tot": 47, "rank_excl": 36, "bestrank": 30, "avgrank": 53.263157894736835}], "8": [{"id": "team52", "name": "Anonymous PD", "institute": "Bodoni, Parma", "inst_id": "prtd04000q", "region": "emi", "fullregion": "Emilia Romagna", "coach": "Rossi Nicoletta", "members": "", "finalist": false, "medals": [0, 0, 0, 1], "rank_reg": 27, "rank_tot": 171, "rank_excl": 153, "bestrank": 106, "avgrank": 49.859154929577464}, {"id": "team53", "name": "I Lo Hacker", "institute": "Bodoni, Parma", "inst_id": "prtd04000q", "region": "emi", "fullregion": "Emilia Romagna", "coach": "Rossi Nicoletta", "members": "", "finalist": false, "medals": [0, 0, 0, 1], "rank_reg": 21, "rank_tot": 131, "rank_excl": 115, "bestrank": 106, "avgrank": 51.64319248826291}], "9": [{"id": "emi46", "name": "Bodoni", "institute": "Bodoni, Parma", "inst_id": "prtd04000q", "region": "emi", "fullregion": "Emilia-Romagna", "coach": "Rossi Nicoletta", "members": "", "finalist": false, "medals": [0, 0, 0, 0], "rank_reg": 56, "rank_tot": 317, "rank_excl": 296, "bestrank": 184, "avgrank": 28.217426059152686}], "10": [{"id": "emi37", "name": "Divoratori di tastiere", "institute": "Bodoni, Parma", "inst_id": "prtd04000q", "region": "emi", "fullregion": "Emilia Romagna", "coach": "Rossi Nicoletta", "members": "", "finalist": false, "medals": [0, 0, 0, 0], "rank_reg": 50, "rank_tot": 287, "rank_excl": 266, "bestrank": 184, "avgrank": 16.119402985074615}, {"id": "emi38", "name": "Level up", "institute": "Bodoni, Parma", "inst_id": "prtd04000q", "region": "emi", "fullregion": "Emilia Romagna", "coach": "Rossi Nicoletta", "members": "", "finalist": false, "medals": [0, 0, 0, 1], "rank_reg": 41, "rank_tot": 242, "rank_excl": 221, "bestrank": 96, "avgrank": 26.069651741293526}]}, "bestrank": 30, "bestavgrank": "53.26%", "avgrank": "37.53%", "participations": [6, 8, 9, 10], "teams": 6}