{"name": "Liceo Orazio Grassi", "city": "Savona", "region": "lig", "fullregion": "Liguria", "medals": [0, 8, 21, 19], "editions": [{"num": 15, "title": "15th Edition", "year": "2023/24", "teams": [{"id": "t-lig-014", "name": "Orazi Grassi", "institute": "Liceo Orazio Grassi, Savona", "inst_id": "svps01000v", "region": "lig", "fullregion": "Liguria", "coach": "Fabio Lanza", "members": "", "finalist": null, "medals": [0, 0, 1, 2], "rank_reg": 4, "rank_tot": 118, "rank_excl": 100, "bestrank": 59, "avgrank": 84.52647278150634, "points": 578, "edition": 15}, {"id": "t-lig-015", "name": "Pitoni", "institute": "Liceo Orazio Grassi, Savona", "inst_id": "svps01000v", "region": "lig", "fullregion": "Liguria", "coach": "Fabio Lanza", "members": "", "finalist": null, "medals": [0, 0, 0, 1], "rank_reg": 5, "rank_tot": 314, "rank_excl": 293, "bestrank": 162, "avgrank": 68.56823266219239, "points": 264, "edition": 15}, {"id": "t-lig-011", "name": "Anaconde", "institute": "Liceo Orazio Grassi, Savona", "inst_id": "svps01000v", "region": "lig", "fullregion": "Liguria", "coach": "Fabio Lanza", "members": "", "finalist": null, "medals": [0, 0, 0, 1], "rank_reg": 6, "rank_tot": 338, "rank_excl": 317, "bestrank": 162, "avgrank": 66.66666666666666, "points": 238, "edition": 15}, {"id": "t-lig-013", "name": "Lombrichi", "institute": "Liceo Orazio Grassi, Savona", "inst_id": "svps01000v", "region": "lig", "fullregion": "Liguria", "coach": "Fabio Lanza", "members": "", "finalist": null, "medals": [0, 0, 0, 1], "rank_reg": 7, "rank_tot": 408, "rank_excl": 387, "bestrank": 162, "avgrank": 62.751677852349, "points": 189, "edition": 15}, {"id": "t-lig-012", "name": "Curiazi Magri", "institute": "Liceo Orazio Grassi, Savona", "inst_id": "svps01000v", "region": "lig", "fullregion": "Liguria", "coach": "Fabio Lanza", "members": "", "finalist": null, "medals": [0, 0, 0, 0], "rank_reg": 8, "rank_tot": 560, "rank_excl": 539, "bestrank": 384, "avgrank": 48.62043251304996, "points": 90, "edition": 15}], "medals": [0, 0, 1, 5], "points": 1359, "avgrank": 66.22669649515288}, {"num": 14, "title": "14th Edition", "year": "2022/23", "teams": [{"id": "t-lig-012", "name": "Orazi Grassi", "institute": "Liceo Orazio Grassi, Savona", "inst_id": "svps01000v", "region": "lig", "fullregion": "Liguria", "coach": "Fabio Lanza", "members": "", "finalist": false, "medals": [0, 2, 1, 1], "rank_reg": 3, "rank_tot": 79, "rank_excl": 59, "bestrank": 35, "avgrank": 87.41372310190825, "points": 1185, "edition": 14}, {"id": "t-lig-011", "name": "Pitoni Grassi", "institute": "Liceo Orazio Grassi, Savona", "inst_id": "svps01000v", "region": "lig", "fullregion": "Liguria", "coach": "Fabio Lanza", "members": "", "finalist": false, "medals": [0, 0, 0, 3], "rank_reg": 6, "rank_tot": 203, "rank_excl": 183, "bestrank": 186, "avgrank": 63.256191636216, "points": 780, "edition": 14}, {"id": "t-lig-013", "name": "Curiazi Magri", "institute": "Liceo Orazio Grassi, Savona", "inst_id": "svps01000v", "region": "lig", "fullregion": "Liguria", "coach": "Fabio Lanza", "members": "", "finalist": false, "medals": [0, 0, 0, 1], "rank_reg": 10, "rank_tot": 279, "rank_excl": 259, "bestrank": 186, "avgrank": 56.232237109216406, "points": 635, "edition": 14}], "medals": [0, 2, 1, 5], "points": 2600, "avgrank": 68.96738394911355}, {"num": 13, "title": "13th Edition", "year": "2021/22", "teams": [{"id": "lig04", "name": "Orazi Grassi", "institute": "Liceo Orazio Grassi, Savona", "inst_id": "svps01000v", "region": "lig", "fullregion": "Liguria", "coach": "Fabio Lanza", "members": "", "finalist": false, "medals": [0, 0, 2, 2], "rank_reg": 3, "rank_tot": 61, "rank_excl": 43, "bestrank": 37, "avgrank": 77.16535433070867, "points": 1261, "edition": 13}, {"id": "lig03", "name": "Curiazi Magri", "institute": "Liceo Orazio Grassi, Savona", "inst_id": "svps01000v", "region": "lig", "fullregion": "Liguria", "coach": "Fabio Lanza", "members": "", "finalist": false, "medals": [0, 0, 0, 0], "rank_reg": 4, "rank_tot": 301, "rank_excl": 280, "bestrank": 240, "avgrank": 29.13385826771652, "points": 330, "edition": 13}], "medals": [0, 0, 2, 2], "points": 1591, "avgrank": 53.14960629921259}, {"num": 12, "title": "12th Edition", "year": "2020/21", "teams": [{"id": "lig04", "name": "Orazi Grassi", "institute": "Liceo Orazio Grassi, Savona", "inst_id": "svps01000v", "region": "lig", "fullregion": "Liguria", "coach": "Fabio Lanza", "members": "", "finalist": false, "medals": [0, 0, 4, 0], "rank_reg": 2, "rank_tot": 28, "rank_excl": 14, "bestrank": 22, "avgrank": 89.39828080229226, "points": 1524, "edition": 12}, {"id": "lig03", "name": "Curiazi Magri", "institute": "Liceo Orazio Grassi, Savona", "inst_id": "svps01000v", "region": "lig", "fullregion": "Liguria", "coach": "Fabio Lanza", "members": "", "finalist": false, "medals": [0, 0, 0, 1], "rank_reg": 4, "rank_tot": 197, "rank_excl": 176, "bestrank": 91, "avgrank": 30.85004775549187, "points": 375, "edition": 12}], "medals": [0, 0, 4, 1], "points": 1899, "avgrank": 60.12416427889207}, {"num": 11, "title": "11th Edition", "year": "2019/20", "teams": [{"id": "lig07", "name": "Orazi Grassi", "institute": "Liceo Orazio Grassi, Savona", "inst_id": "svps01000v", "region": "lig", "fullregion": "Liguria", "coach": "Fabio Lanza", "members": "", "finalist": true, "medals": [0, 2, 2, 0], "rank_reg": 1, "rank_tot": 22, "rank_excl": 0, "bestrank": 23, "avgrank": 94.73267326732673, "points": 2095, "edition": 11}, {"id": "lig06", "name": "Curiazi Magri", "institute": "Liceo Orazio Grassi, Savona", "inst_id": "svps01000v", "region": "lig", "fullregion": "Liguria", "coach": "Fabio Lanza", "members": "", "finalist": false, "medals": [0, 0, 2, 1], "rank_reg": 3, "rank_tot": 73, "rank_excl": 55, "bestrank": 52, "avgrank": 75.24752475247524, "points": 1300, "edition": 11}], "medals": [0, 2, 4, 1], "points": 3395, "avgrank": 84.99009900990099}, {"num": 10, "title": "10th Edition", "year": "2018/19", "teams": [{"id": "lig02", "name": "Orazi Grassi", "institute": "Liceo Orazio Grassi, Savona", "inst_id": "svps01000v", "region": "lig", "fullregion": "Liguria", "coach": "Fabio Lanza", "members": "", "finalist": true, "medals": [0, 0, 2, 2], "rank_reg": 1, "rank_tot": 32, "rank_excl": 0, "bestrank": 21, "avgrank": 86.01190476190476, "points": 1527, "edition": 10}, {"id": "lig01", "name": "Curiazi Magri", "institute": "Liceo Orazio Grassi, Savona", "inst_id": "svps01000v", "region": "lig", "fullregion": "Liguria", "coach": "Fabio Lanza", "members": "", "finalist": false, "medals": [0, 0, 1, 2], "rank_reg": 2, "rank_tot": 61, "rank_excl": 43, "bestrank": 34, "avgrank": 74.2063492063492, "points": 1005, "edition": 10}], "medals": [0, 0, 3, 4], "points": 2532, "avgrank": 80.10912698412699}, {"num": 9, "title": "9th Edition", "year": "2017/18", "teams": [{"id": "lig06", "name": "I Curiazi Magri", "institute": "Liceo Orazio Grassi, Savona", "inst_id": "svps01000v", "region": "lig", "fullregion": "Liguria", "coach": "Fabio Lanza", "members": "", "finalist": true, "medals": [0, 0, 3, 1], "rank_reg": 1, "rank_tot": 53, "rank_excl": 0, "bestrank": 29, "avgrank": 86.45933014354067, "points": 965, "edition": 9}, {"id": "lig05", "name": "Gli Orazi Grassi", "institute": "Liceo Orazio Grassi, Savona", "inst_id": "svps01000v", "region": "lig", "fullregion": "Liguria", "coach": "Fabio Lanza", "members": "", "finalist": false, "medals": [0, 0, 3, 0], "rank_reg": 2, "rank_tot": 63, "rank_excl": 47, "bestrank": 36, "avgrank": 74.32216905901116, "points": 845, "edition": 9}], "medals": [0, 0, 6, 1], "points": 1810, "avgrank": 80.39074960127591}, {"num": 8, "title": "8th Edition", "year": "2016/17", "teams": [{"id": "team211", "name": "Liceo Grassi Savona", "institute": "Liceo Orazio Grassi, Savona", "inst_id": "svps01000v", "region": "lig", "fullregion": "Liguria", "coach": "Fabio Lanza", "members": "", "finalist": true, "medals": [0, 4, 0, 0], "rank_reg": 1, "rank_tot": 5, "rank_excl": 0, "bestrank": 5, "avgrank": 97.07865168539325, "points": 1857, "edition": 8}], "medals": [0, 4, 0, 0], "points": 1857, "avgrank": 97.07865168539325}], "bestedrank": 5, "bestrank": 5, "bestavgrank": 97.07865168539325, "avgrank": 71.1916725450166, "points": 17043, "participations": [8, 9, 10, 11, 12, 13, 14, 15], "teams": 19, "highlights": [{"id": "/edition/8/team/team211", "name": "Liceo Grassi Savona", "description": "is the team with the best awards (4), rank (5) and average rank (97%)"}, {"id": "/edition/8", "name": "OIS 2016/17", "description": "is the edition with the most points per team (1857), average rank (97%) and awards (4)"}, {"id": "/edition/11/team/lig07", "name": "Orazi Grassi", "description": "is the team with the most total points (2095)"}]}