{"name": "C. Pisacane", "city": "Padula", "region": "cam", "fullregion": "Campania", "medals": [0, 3, 2, 3], "editions": [{"num": 15, "title": "15th Edition", "year": "2023/24", "teams": [{"id": "t-cam-038", "name": "CTRLFreak", "institute": "C. Pisacane, Padula", "inst_id": "saps070007", "region": "cam", "fullregion": "Campania", "coach": "Chiara Chirichella", "members": "", "finalist": null, "medals": [0, 1, 1, 2], "rank_reg": 3, "rank_tot": 86, "rank_excl": 69, "bestrank": 31, "avgrank": 86.91275167785236, "points": 889, "edition": 15}, {"id": "t-cam-039", "name": "KKK", "institute": "C. Pisacane, Padula", "inst_id": "saps070007", "region": "cam", "fullregion": "Campania", "coach": "Chiara Chirichella", "members": "", "finalist": null, "medals": [0, 0, 0, 0], "rank_reg": 26, "rank_tot": 587, "rank_excl": 566, "bestrank": 350, "avgrank": 50.39149888143177, "points": 75, "edition": 15}], "medals": [0, 1, 1, 2], "points": 964, "avgrank": 68.65212527964206}, {"num": 14, "title": "14th Edition", "year": "2022/23", "teams": [{"id": "t-cam-070", "name": "PisHack", "institute": "C. Pisacane, Padula", "inst_id": "saps070007", "region": "cam", "fullregion": "Campania", "coach": "Chiara Chirichella", "members": "", "finalist": true, "medals": [0, 2, 1, 1], "rank_reg": 1, "rank_tot": 41, "rank_excl": 0, "bestrank": 16, "avgrank": 93.25213154689403, "points": 1502, "edition": 14}, {"id": "t-cam-069", "name": "MartianHackers", "institute": "C. Pisacane, Padula", "inst_id": "saps070007", "region": "cam", "fullregion": "Campania", "coach": "Chiara Chirichella", "members": "", "finalist": false, "medals": [0, 0, 0, 0], "rank_reg": 45, "rank_tot": 662, "rank_excl": 641, "bestrank": 419, "avgrank": 16.727568006496142, "points": 0, "edition": 14}], "medals": [0, 2, 1, 1], "points": 1502, "avgrank": 54.98984977669509}], "bestedrank": 41, "bestrank": 16, "bestavgrank": 93.25213154689403, "avgrank": 61.82098752816858, "points": 2466, "participations": [14, 15], "teams": 4, "highlights": [{"id": "/edition/14/team/t-cam-070", "name": "PisHack", "description": "is the team with the best awards (4), rank (41), regional rank (1), average rank (93%) and total points (1502)"}, {"id": "/edition/14", "name": "OIS 2022/23", "description": "is the edition with the most points per team (751), total points (1502) and awards (4)"}, {"id": "/edition/15", "name": "OIS 2023/24", "description": "is the edition with the highest average rank (69%)"}]}