{"name": "I.T.T. E. Ferrari", "city": "Lauria", "region": "bas", "fullregion": "Basilicata", "medals": [0, 0, 0, 0], "editions": {"11": [{"id": "bas02", "name": "FdP", "institute": "I.T.T. E. Ferrari, Lauria", "inst_id": "pztf00601v", "region": "bas", "fullregion": "Basilicata", "coach": "Ponzio Teresa", "members": "", "finalist": null, "medals": [0, 0, 0, 0], "rank_reg": 1, "rank_tot": 170, "rank_excl": 0, "bestrank": 170, "avgrank": 66.53465346534654}]}, "bestrank": 170, "bestavgrank": "66.53%", "avgrank": "66.53%", "participations": [11], "teams": 1}