{"name": "Statale A.di Savoia", "city": "Pistoia", "region": "tos", "fullregion": "Toscana", "medals": [0, 2, 3, 2], "editions": [{"num": 15, "title": "15th Edition", "year": "2023/24", "teams": [{"id": "t-tos-043", "name": "InforMat", "institute": "Statale A.di Savoia, Pistoia", "inst_id": "ptps01000p", "region": "tos", "fullregion": "Toscana", "coach": "Francesco Mogavero", "members": "", "finalist": null, "medals": [0, 1, 0, 0], "rank_reg": 3, "rank_tot": 20, "rank_excl": 10, "bestrank": 20, "avgrank": 97.76286353467562, "points": 375, "edition": 15}, {"id": "t-tos-044", "name": "unheimlich", "institute": "Statale A.di Savoia, Pistoia", "inst_id": "ptps01000p", "region": "tos", "fullregion": "Toscana", "coach": "Francesco Mogavero", "members": "", "finalist": null, "medals": [0, 0, 1, 0], "rank_reg": 8, "rank_tot": 124, "rank_excl": 104, "bestrank": 124, "avgrank": 86.12975391498881, "points": 190, "edition": 15}, {"id": "t-tos-042", "name": "Frogs", "institute": "Statale A.di Savoia, Pistoia", "inst_id": "ptps01000p", "region": "tos", "fullregion": "Toscana", "coach": "Francesco Mogavero", "members": "", "finalist": null, "medals": [0, 0, 0, 1], "rank_reg": 10, "rank_tot": 152, "rank_excl": 131, "bestrank": 152, "avgrank": 82.99776286353467, "points": 165, "edition": 15}, {"id": "t-tos-041", "name": "DSA", "institute": "Statale A.di Savoia, Pistoia", "inst_id": "ptps01000p", "region": "tos", "fullregion": "Toscana", "coach": "Francesco Mogavero", "members": "", "finalist": null, "medals": [0, 0, 0, 0], "rank_reg": 30, "rank_tot": 400, "rank_excl": 378, "bestrank": 400, "avgrank": 55.257270693512304, "points": 58, "edition": 15}], "medals": [0, 1, 1, 1], "points": 788, "avgrank": 80.53691275167785}, {"num": 14, "title": "14th Edition", "year": "2022/23", "teams": [{"id": "t-tos-033", "name": "Liceo Scientifico Amedeo Di Savoia", "institute": "Statale A.di Savoia, Pistoia", "inst_id": "ptps01000p", "region": "tos", "fullregion": "Toscana", "coach": "Francesco Mogavero", "members": "", "finalist": false, "medals": [0, 1, 2, 1], "rank_reg": 6, "rank_tot": 56, "rank_excl": 39, "bestrank": 35, "avgrank": 85.74908647990256, "points": 1298, "edition": 14}], "medals": [0, 1, 2, 1], "points": 1298, "avgrank": 85.74908647990256}], "bestedrank": 20, "bestrank": 20, "bestavgrank": 97.76286353467562, "avgrank": 81.57934749732279, "points": 2086, "participations": [14, 15], "teams": 5, "highlights": [{"id": "/edition/15/team/t-tos-043", "name": "InforMat", "description": "is the team with the highest rank (20), regional rank (3) and average rank (98%)"}, {"id": "/edition/14", "name": "OIS 2022/23", "description": "is the edition with the most points per team (1298), average rank (86%), total points (1298) and awards (4)"}, {"id": "/edition/14/team/t-tos-033", "name": "Liceo Scientifico Amedeo Di Savoia", "description": "is the team with the best awards (4) and total points (1298)"}]}