{"name": "ITI Cannizzaro", "city": "Catania", "region": "sic", "fullregion": "Sicilia", "medals": [0, 0, 0, 0], "editions": {"6": [{"id": "vaiquieh", "name": "3INFOCANNI", "institute": "ITI Cannizzaro, Catania", "inst_id": "cttf03000r", "region": "sic", "fullregion": "Sicilia", "coach": "", "members": "", "finalist": true, "medals": [0, 0, 0, 0], "rank_reg": 4, "rank_tot": 69, "rank_excl": 58, "bestrank": 34, "avgrank": 42.3157894736842}, {"id": "hiebahmi", "name": "4INFOCANNI", "institute": "ITI Cannizzaro, Catania", "inst_id": "cttf03000r", "region": "sic", "fullregion": "Sicilia", "coach": "", "members": "", "finalist": true, "medals": [0, 0, 0, 0], "rank_reg": 3, "rank_tot": 64, "rank_excl": 53, "bestrank": 34, "avgrank": 43.1578947368421}], "7": [{"id": "team193", "name": "Cann4A", "institute": "ITI Cannizzaro, Catania", "inst_id": "cttf03000r", "region": "sic", "fullregion": "Sicilia", "coach": "", "members": "", "finalist": false, "medals": [0, 0, 0, 0], "rank_reg": 4, "rank_tot": 99, "rank_excl": 86, "bestrank": 65, "avgrank": 42.10526315789473}, {"id": "team194", "name": "Cann4B", "institute": "ITI Cannizzaro, Catania", "inst_id": "cttf03000r", "region": "sic", "fullregion": "Sicilia", "coach": "", "members": "", "finalist": false, "medals": [0, 0, 0, 0], "rank_reg": 10, "rank_tot": 170, "rank_excl": 156, "bestrank": 106, "avgrank": 21.69059011164275}, {"id": "team195", "name": "Cann4C", "institute": "ITI Cannizzaro, Catania", "inst_id": "cttf03000r", "region": "sic", "fullregion": "Sicilia", "coach": "", "members": "", "finalist": false, "medals": [0, 0, 0, 0], "rank_reg": 10, "rank_tot": 170, "rank_excl": 156, "bestrank": 106, "avgrank": 21.690590111642734}]}, "bestrank": 34, "bestavgrank": "43.16%", "avgrank": "34.19%", "participations": [6, 7], "teams": 5}