{"name": "Marche", "medals": [0, 0, 17, 18], "institutes": [{"name": "I.I.S. Volterra - Elia", "city": "Ancona", "region": "mar", "fullregion": "Marche", "medals": [0, 0, 9, 6], "bestedrank": 26, "bestrank": 22, "bestavgrank": 94.0828402366864, "avgrank": 44.62474015938869, "points": 6861, "participations": [11, 12, 13], "teams": 16, "id": "anis014007"}, {"name": "G. Galilei", "city": "Ancona", "region": "mar", "fullregion": "Marche", "medals": [0, 0, 8, 9], "bestedrank": 34, "bestrank": 16, "bestavgrank": 87.88059701492537, "avgrank": 73.92089680086279, "points": 5541, "participations": [9, 10, 11, 12, 13], "teams": 6, "id": "anps03000e"}, {"name": "L.di Savoia - G. Benincasa", "city": "Ancona", "region": "mar", "fullregion": "Marche", "medals": [0, 0, 0, 2], "bestedrank": 166, "bestrank": 66, "bestavgrank": 65.28599605522683, "avgrank": 25.798482357880832, "points": 1574, "participations": [10, 12, 13], "teams": 13, "id": "anis01200g"}, {"name": "Enrico Mattei", "city": "Recanati", "region": "mar", "fullregion": "Marche", "medals": [0, 0, 0, 1], "bestedrank": 34, "bestrank": 28, "bestavgrank": 63.368421052631575, "avgrank": 40.63157894736842, "points": 1940, "participations": [6], "teams": 3, "id": "mcis00400a"}], "participations": [6, 9, 10, 11, 12, 13], "teams": 38, "bestedrank": 26, "bestrank": 16, "bestbestavgrank": 94.0828402366864, "bestavgrank": 73.92089680086279, "avgrank": 46.243924566375185, "points": 15916, "instnum": 4, "id": "mar", "highlights": [{"id": "/region/mar/anis014007", "name": "I.I.S. Volterra - Elia", "description": "is the school with the most teams (16), total points (6861), average rank (94%) and awards (15)"}, {"id": "/edition/12/team/mar06", "name": "Vol_Elia01", "description": "is the team with the most total points (1554) and rank (26)"}, {"id": "/region/mar/anps03000e", "name": "G. Galilei", "description": "is the school with the most points per team (924)"}]}