{"name": "Liceo Statale G. Guacci", "city": "Benevento", "region": "cam", "fullregion": "Campania", "medals": [0, 0, 0, 2], "editions": [{"num": 14, "title": "14th Edition", "year": "2022/23", "teams": [{"id": "t-cam-018", "name": "Tech4Chad", "institute": "Liceo Statale G. Guacci, Benevento", "inst_id": "bnpm02000t", "region": "cam", "fullregion": "Campania", "coach": "Daniele Pescatore", "members": "", "finalist": null, "medals": [0, 0, 0, 1], "rank_reg": 8, "rank_tot": 350, "rank_excl": 329, "bestrank": 186, "avgrank": 63.76370280146163, "points": 530, "edition": 14}, {"id": "t-cam-017", "name": "I Dottori", "institute": "Liceo Statale G. Guacci, Benevento", "inst_id": "bnpm02000t", "region": "cam", "fullregion": "Campania", "coach": "Daniele Pescatore", "members": "", "finalist": null, "medals": [0, 0, 0, 1], "rank_reg": 20, "rank_tot": 491, "rank_excl": 470, "bestrank": 186, "avgrank": 51.58343483556638, "points": 315, "edition": 14}, {"id": "t-cam-016", "name": "Brothers Tech", "institute": "Liceo Statale G. Guacci, Benevento", "inst_id": "bnpm02000t", "region": "cam", "fullregion": "Campania", "coach": "Daniele Pescatore", "members": "", "finalist": null, "medals": [0, 0, 0, 0], "rank_reg": 27, "rank_tot": 545, "rank_excl": 524, "bestrank": 309, "avgrank": 43.66626065773447, "points": 215, "edition": 14}], "medals": [0, 0, 0, 2], "points": 1060, "avgrank": 53.00446609825416}], "bestedrank": 350, "bestrank": 186, "bestavgrank": 63.76370280146163, "avgrank": 53.00446609825416, "points": 1060, "participations": [14], "teams": 3, "highlights": [{"id": "/edition/14/team/t-cam-018", "name": "Tech4Chad", "description": "is the team with the highest rank (350), regional rank (8), average rank (64%) and total points (530)"}, {"id": "/edition/14", "name": "OIS 2022/23", "description": "is the edition with the most points per team (353), average rank (53%), total points (1060), teams (3) and awards (2)"}]}