{"name": "Liceo Scientifico Statale Lorenzo Mossa", "city": "Olbia", "region": "sar", "fullregion": "Sardegna", "medals": [0, 0, 0, 0], "editions": [{"num": 14, "title": "14th Edition", "year": "2022/23", "teams": [{"id": "t-sar-003", "name": "scientifico Olbia", "institute": "Liceo Scientifico Statale Lorenzo Mossa, Olbia", "inst_id": "ssps05000g", "region": "sar", "fullregion": "Sardegna", "coach": "Andrea Corigliano", "members": "", "finalist": null, "medals": [0, 0, 0, 0], "rank_reg": 7, "rank_tot": 342, "rank_excl": 319, "bestrank": 342, "avgrank": 58.41463414634146, "points": 135, "edition": 14}], "medals": [0, 0, 0, 0], "points": 135, "avgrank": 58.41463414634146}], "bestedrank": 342, "bestrank": 342, "bestavgrank": 58.41463414634146, "avgrank": 58.41463414634146, "points": 135, "participations": [14], "teams": 1, "highlights": [{"id": "/edition/14/team/t-sar-003", "name": "scientifico Olbia", "description": "is the team with the best awards (0), rank (342), regional rank (7), average rank (58%) and total points (135)"}, {"id": "/edition/14", "name": "OIS 2022/23", "description": "is the edition with the most points per team (135), average rank (58%), total points (135), teams (1) and awards (0)"}]}