{"name": "L. Scient. \"Carlo Urbani\"San Giorgio A Cr.", "city": "San Giorgio A Cremano", "region": "cam", "fullregion": "Campania", "medals": [0, 1, 2, 4], "editions": [{"num": 15, "title": "15th Edition", "year": "2023/24", "teams": [{"id": "t-cam-042", "name": "Cava de' Terroni", "institute": "L. Scient. \"Carlo Urbani\"San Giorgio A Cr., San Giorgio A Cremano", "inst_id": "naps36000r", "region": "cam", "fullregion": "Campania", "coach": "Ottavio Gelone", "members": "", "finalist": null, "medals": [0, 1, 1, 0], "rank_reg": 1, "rank_tot": 40, "rank_excl": 0, "bestrank": 24, "avgrank": 93.95973154362416, "points": 537, "edition": 15}, {"id": "t-cam-043", "name": "Gel1", "institute": "L. Scient. \"Carlo Urbani\"San Giorgio A Cr., San Giorgio A Cremano", "inst_id": "naps36000r", "region": "cam", "fullregion": "Campania", "coach": "Ottavio Gelone", "members": "", "finalist": null, "medals": [0, 0, 0, 1], "rank_reg": 5, "rank_tot": 283, "rank_excl": 262, "bestrank": 162, "avgrank": 72.87472035794184, "points": 168, "edition": 15}, {"id": "t-cam-045", "name": "Obamna Prism", "institute": "L. Scient. \"Carlo Urbani\"San Giorgio A Cr., San Giorgio A Cremano", "inst_id": "naps36000r", "region": "cam", "fullregion": "Campania", "coach": "Ottavio Gelone", "members": "", "finalist": null, "medals": [0, 0, 0, 1], "rank_reg": 14, "rank_tot": 402, "rank_excl": 381, "bestrank": 162, "avgrank": 60.06711409395973, "points": 100, "edition": 15}, {"id": "t-cam-046", "name": "Stai di-struct", "institute": "L. Scient. \"Carlo Urbani\"San Giorgio A Cr., San Giorgio A Cremano", "inst_id": "naps36000r", "region": "cam", "fullregion": "Campania", "coach": "Ottavio Gelone", "members": "", "finalist": null, "medals": [0, 0, 0, 1], "rank_reg": 14, "rank_tot": 402, "rank_excl": 381, "bestrank": 162, "avgrank": 60.06711409395973, "points": 100, "edition": 15}, {"id": "t-cam-040", "name": "ARRAY-VEDERCI", "institute": "L. Scient. \"Carlo Urbani\"San Giorgio A Cr., San Giorgio A Cremano", "inst_id": "naps36000r", "region": "cam", "fullregion": "Campania", "coach": "Ottavio Gelone", "members": "", "finalist": null, "medals": [0, 0, 0, 0], "rank_reg": 30, "rank_tot": 654, "rank_excl": 633, "bestrank": 507, "avgrank": 40.771812080536904, "points": 0, "edition": 15}, {"id": "t-cam-041", "name": "boom.exe", "institute": "L. Scient. \"Carlo Urbani\"San Giorgio A Cr., San Giorgio A Cremano", "inst_id": "naps36000r", "region": "cam", "fullregion": "Campania", "coach": "Ottavio Gelone", "members": "", "finalist": null, "medals": [0, 0, 0, 0], "rank_reg": 30, "rank_tot": 654, "rank_excl": 633, "bestrank": 507, "avgrank": 40.771812080536904, "points": 0, "edition": 15}, {"id": "t-cam-044", "name": "Gelaviottoni", "institute": "L. Scient. \"Carlo Urbani\"San Giorgio A Cr., San Giorgio A Cremano", "inst_id": "naps36000r", "region": "cam", "fullregion": "Campania", "coach": "Ottavio Gelone", "members": "", "finalist": null, "medals": [0, 0, 0, 0], "rank_reg": 30, "rank_tot": 654, "rank_excl": 633, "bestrank": 507, "avgrank": 40.771812080536904, "points": 0, "edition": 15}, {"id": "t-cam-047", "name": "TuWi-FiLamericano", "institute": "L. Scient. \"Carlo Urbani\"San Giorgio A Cr., San Giorgio A Cremano", "inst_id": "naps36000r", "region": "cam", "fullregion": "Campania", "coach": "Ottavio Gelone", "members": "", "finalist": null, "medals": [0, 0, 0, 0], "rank_reg": 30, "rank_tot": 654, "rank_excl": 633, "bestrank": 507, "avgrank": 40.771812080536904, "points": 0, "edition": 15}], "medals": [0, 1, 1, 3], "points": 905, "avgrank": 56.256991051454136}, {"num": 14, "title": "14th Edition", "year": "2022/23", "teams": [{"id": "t-cam-075", "name": "Quicksilver Snakes", "institute": "L. Scient. \"Carlo Urbani\"San Giorgio A Cr., San Giorgio A Cremano", "inst_id": "naps36000r", "region": "cam", "fullregion": "Campania", "coach": "Giovanni Piazzullo", "members": "", "finalist": false, "medals": [0, 0, 1, 0], "rank_reg": 15, "rank_tot": 461, "rank_excl": 440, "bestrank": 97, "avgrank": 37.19041818920016, "points": 355, "edition": 14}, {"id": "t-cam-073", "name": "Hot Rockets", "institute": "L. Scient. \"Carlo Urbani\"San Giorgio A Cr., San Giorgio A Cremano", "inst_id": "naps36000r", "region": "cam", "fullregion": "Campania", "coach": "Giovanni Piazzullo", "members": "", "finalist": false, "medals": [0, 0, 0, 1], "rank_reg": 23, "rank_tot": 502, "rank_excl": 481, "bestrank": 224, "avgrank": 36.012992285830286, "points": 300, "edition": 14}, {"id": "t-cam-076", "name": "Black Buccaneers", "institute": "L. Scient. \"Carlo Urbani\"San Giorgio A Cr., San Giorgio A Cremano", "inst_id": "naps36000r", "region": "cam", "fullregion": "Campania", "coach": "Giovanni Piazzullo", "members": "", "finalist": false, "medals": [0, 0, 0, 0], "rank_reg": 29, "rank_tot": 559, "rank_excl": 538, "bestrank": 348, "avgrank": 30.978481526593583, "points": 200, "edition": 14}, {"id": "t-cam-072", "name": "The Busters", "institute": "L. Scient. \"Carlo Urbani\"San Giorgio A Cr., San Giorgio A Cremano", "inst_id": "naps36000r", "region": "cam", "fullregion": "Campania", "coach": "Giovanni Piazzullo", "members": "", "finalist": false, "medals": [0, 0, 0, 0], "rank_reg": 35, "rank_tot": 604, "rank_excl": 583, "bestrank": 348, "avgrank": 25.253755582622816, "points": 100, "edition": 14}, {"id": "t-cam-078", "name": "Red Panthers", "institute": "L. Scient. \"Carlo Urbani\"San Giorgio A Cr., San Giorgio A Cremano", "inst_id": "naps36000r", "region": "cam", "fullregion": "Campania", "coach": "Giovanni Piazzullo", "members": "", "finalist": false, "medals": [0, 0, 0, 0], "rank_reg": 35, "rank_tot": 604, "rank_excl": 583, "bestrank": 348, "avgrank": 25.253755582622816, "points": 100, "edition": 14}, {"id": "t-cam-071", "name": "Knockout Executioners", "institute": "L. Scient. \"Carlo Urbani\"San Giorgio A Cr., San Giorgio A Cremano", "inst_id": "naps36000r", "region": "cam", "fullregion": "Campania", "coach": "Giovanni Piazzullo", "members": "", "finalist": false, "medals": [0, 0, 0, 0], "rank_reg": 45, "rank_tot": 662, "rank_excl": 641, "bestrank": 419, "avgrank": 16.727568006496142, "points": 0, "edition": 14}, {"id": "t-cam-074", "name": "Thunder Lightning", "institute": "L. Scient. \"Carlo Urbani\"San Giorgio A Cr., San Giorgio A Cremano", "inst_id": "naps36000r", "region": "cam", "fullregion": "Campania", "coach": "Giovanni Piazzullo", "members": "", "finalist": false, "medals": [0, 0, 0, 0], "rank_reg": 45, "rank_tot": 662, "rank_excl": 641, "bestrank": 419, "avgrank": 16.727568006496142, "points": 0, "edition": 14}, {"id": "t-cam-077", "name": "Zulu Soldiers", "institute": "L. Scient. \"Carlo Urbani\"San Giorgio A Cr., San Giorgio A Cremano", "inst_id": "naps36000r", "region": "cam", "fullregion": "Campania", "coach": "Giovanni Piazzullo", "members": "", "finalist": false, "medals": [0, 0, 0, 0], "rank_reg": 45, "rank_tot": 662, "rank_excl": 641, "bestrank": 419, "avgrank": 16.727568006496142, "points": 0, "edition": 14}, {"id": "t-cam-079", "name": "Raging Secret Agents", "institute": "L. Scient. \"Carlo Urbani\"San Giorgio A Cr., San Giorgio A Cremano", "inst_id": "naps36000r", "region": "cam", "fullregion": "Campania", "coach": "Giovanni Piazzullo", "members": "", "finalist": false, "medals": [0, 0, 0, 0], "rank_reg": 45, "rank_tot": 662, "rank_excl": 641, "bestrank": 419, "avgrank": 16.727568006496142, "points": 0, "edition": 14}], "medals": [0, 0, 1, 1], "points": 1055, "avgrank": 24.622186132539362}], "bestedrank": 40, "bestrank": 24, "bestavgrank": 93.95973154362416, "avgrank": 39.50915315320514, "points": 1960, "participations": [14, 15], "teams": 17, "highlights": [{"id": "/edition/15/team/t-cam-042", "name": "Cava de' Terroni", "description": "is the team with the best awards (2), rank (40), regional rank (1), average rank (94%) and total points (537)"}, {"id": "/edition/14", "name": "OIS 2022/23", "description": "is the edition with the most points per team (117), total points (1055) and teams (9)"}, {"id": "/edition/15", "name": "OIS 2023/24", "description": "is the edition with the highest average rank (56%) and awards (5)"}]}