{"name": "G.B.B. Lucarelli", "city": "Benevento", "region": "cam", "fullregion": "Campania", "medals": [0, 0, 0, 4], "editions": [{"num": 15, "title": "15th Edition", "year": "2023/24", "teams": [{"id": "t-cam-005", "name": "codecrafters", "institute": "G.B.B. Lucarelli, Benevento", "inst_id": "bntf010008", "region": "cam", "fullregion": "Campania", "coach": "Ester Giallonardo", "members": "", "finalist": null, "medals": [0, 0, 0, 1], "rank_reg": 8, "rank_tot": 333, "rank_excl": 312, "bestrank": 162, "avgrank": 67.39373601789708, "points": 133, "edition": 15}, {"id": "t-cam-006", "name": "CyberOlympia", "institute": "G.B.B. Lucarelli, Benevento", "inst_id": "bntf010008", "region": "cam", "fullregion": "Campania", "coach": "Ester Giallonardo", "members": "", "finalist": null, "medals": [0, 0, 0, 1], "rank_reg": 8, "rank_tot": 333, "rank_excl": 312, "bestrank": 162, "avgrank": 67.39373601789708, "points": 133, "edition": 15}, {"id": "t-cam-008", "name": "STARDUST CRUSADERS", "institute": "G.B.B. Lucarelli, Benevento", "inst_id": "bntf010008", "region": "cam", "fullregion": "Campania", "coach": "Ester Giallonardo", "members": "", "finalist": null, "medals": [0, 0, 0, 1], "rank_reg": 11, "rank_tot": 370, "rank_excl": 349, "bestrank": 162, "avgrank": 61.74496644295302, "points": 130, "edition": 15}, {"id": "t-cam-004", "name": "Bit Busters", "institute": "G.B.B. Lucarelli, Benevento", "inst_id": "bntf010008", "region": "cam", "fullregion": "Campania", "coach": "Ester Giallonardo", "members": "", "finalist": null, "medals": [0, 0, 0, 1], "rank_reg": 14, "rank_tot": 402, "rank_excl": 381, "bestrank": 162, "avgrank": 60.06711409395973, "points": 100, "edition": 15}, {"id": "t-cam-007", "name": "Dream Team", "institute": "G.B.B. Lucarelli, Benevento", "inst_id": "bntf010008", "region": "cam", "fullregion": "Campania", "coach": "Ester Giallonardo", "members": "", "finalist": null, "medals": [0, 0, 0, 0], "rank_reg": 30, "rank_tot": 654, "rank_excl": 633, "bestrank": 507, "avgrank": 40.771812080536904, "points": 0, "edition": 15}], "medals": [0, 0, 0, 4], "points": 496, "avgrank": 59.47427293064876}, {"num": 14, "title": "14th Edition", "year": "2022/23", "teams": [{"id": "t-cam-015", "name": "4 IB", "institute": "G.B.B. Lucarelli, Benevento", "inst_id": "bntf010008", "region": "cam", "fullregion": "Campania", "coach": "Ester Giallonardo", "members": "", "finalist": false, "medals": [0, 0, 0, 0], "rank_reg": 12, "rank_tot": 427, "rank_excl": 406, "bestrank": 267, "avgrank": 35.93179049939097, "points": 405, "edition": 14}, {"id": "t-cam-014", "name": "he fork(s);", "institute": "G.B.B. Lucarelli, Benevento", "inst_id": "bntf010008", "region": "cam", "fullregion": "Campania", "coach": "Ester Giallonardo", "members": "", "finalist": false, "medals": [0, 0, 0, 0], "rank_reg": 21, "rank_tot": 493, "rank_excl": 472, "bestrank": 347, "avgrank": 28.542427933414544, "points": 310, "edition": 14}, {"id": "t-cam-013", "name": "LMV", "institute": "G.B.B. Lucarelli, Benevento", "inst_id": "bntf010008", "region": "cam", "fullregion": "Campania", "coach": "Ester Giallonardo", "members": "", "finalist": false, "medals": [0, 0, 0, 0], "rank_reg": 35, "rank_tot": 604, "rank_excl": 583, "bestrank": 419, "avgrank": 18.148599269183933, "points": 100, "edition": 14}], "medals": [0, 0, 0, 0], "points": 815, "avgrank": 27.540939233996482}], "bestedrank": 333, "bestrank": 162, "bestavgrank": 67.39373601789708, "avgrank": 47.499272794404156, "points": 1311, "participations": [14, 15], "teams": 8, "highlights": [{"id": "/edition/15", "name": "OIS 2023/24", "description": "is the edition with the highest average rank (59%), teams (5) and awards (4)"}, {"id": "/edition/14", "name": "OIS 2022/23", "description": "is the edition with the most points per team (272) and total points (815)"}, {"id": "/edition/14/team/t-cam-015", "name": "4 IB", "description": "is the team with the most total points (405)"}]}